protoc_gen_swagger/__init__.py
protoc_gen_swagger/options/__init__.py
protoc_gen_swagger/options/annotations_pb2.py
protoc_gen_swagger/options/annotations_pb2.pyi
protoc_gen_swagger/options/annotations_pb2_grpc.py
protoc_gen_swagger/options/openapiv2_pb2.py
protoc_gen_swagger/options/openapiv2_pb2.pyi
protoc_gen_swagger/options/openapiv2_pb2_grpc.py
scanoss/__init__.py
scanoss/cli.py
scanoss/components.py
scanoss/constants.py
scanoss/cryptography.py
scanoss/csvoutput.py
scanoss/cyclonedx.py
scanoss/delta.py
scanoss/file_filters.py
scanoss/filecount.py
scanoss/gitlabqualityreport.py
scanoss/header_filter.py
scanoss/osadl.py
scanoss/results.py
scanoss/scancodedeps.py
scanoss/scanner.py
scanoss/scanoss_settings.py
scanoss/scanossapi.py
scanoss/scanossbase.py
scanoss/scanossgrpc.py
scanoss/scanpostprocessor.py
scanoss/scantype.py
scanoss/spdxlite.py
scanoss/threadeddependencies.py
scanoss/threadedscanning.py
scanoss/winnowing.py
scanoss/api/__init__.py
scanoss/api/common/__init__.py
scanoss/api/common/v2/__init__.py
scanoss/api/common/v2/scanoss_common_pb2.py
scanoss/api/common/v2/scanoss_common_pb2_grpc.py
scanoss/api/components/__init__.py
scanoss/api/components/v2/__init__.py
scanoss/api/components/v2/scanoss_components_pb2.py
scanoss/api/components/v2/scanoss_components_pb2_grpc.py
scanoss/api/cryptography/v2/scanoss_cryptography_pb2.py
scanoss/api/cryptography/v2/scanoss_cryptography_pb2_grpc.py
scanoss/api/dependencies/__init__.py
scanoss/api/dependencies/v2/__init__.py
scanoss/api/dependencies/v2/scanoss_dependencies_pb2.py
scanoss/api/dependencies/v2/scanoss_dependencies_pb2_grpc.py
scanoss/api/geoprovenance/__init__.py
scanoss/api/geoprovenance/v2/__init__.py
scanoss/api/geoprovenance/v2/scanoss_geoprovenance_pb2.py
scanoss/api/geoprovenance/v2/scanoss_geoprovenance_pb2_grpc.py
scanoss/api/licenses/__init__.py
scanoss/api/licenses/v2/__init__.py
scanoss/api/licenses/v2/scanoss_licenses_pb2.py
scanoss/api/licenses/v2/scanoss_licenses_pb2_grpc.py
scanoss-1.44.0.dist-info/licenses/LICENSE
scanoss-1.44.0.dist-info/METADATA
scanoss-1.44.0.dist-info/WHEEL
scanoss-1.44.0.dist-info/entry_points.txt
scanoss-1.44.0.dist-info/top_level.txt
scanoss-1.44.0.dist-info/RECORD
