Metadata-Version: 2.4
Name: scanoss
Version: 1.44.0
Summary: Simple Python library to leverage the SCANOSS APIs
Home-page: https://scanoss.com
Author: SCANOSS
Author-email: info@scanoss.com
License: MIT
Project-URL: Source, https://github.com/scanoss/scanoss.py
Project-URL: Tracker, https://github.com/scanoss/scanoss.py/issues
Classifier: Programming Language :: Python :: 3
Classifier: License :: OSI Approved :: MIT License
Classifier: Operating System :: OS Independent
Classifier: Development Status :: 5 - Production/Stable
Classifier: Programming Language :: Python :: 3
Requires-Python: >=3.9
License-File: LICENSE
Requires-Dist: requests
Requires-Dist: crc32c>=2.2
Requires-Dist: binaryornot
Requires-Dist: progress
Requires-Dist: grpcio>=1.73.1
Requires-Dist: protobuf>=6.3.1
Requires-Dist: protoc-gen-openapiv2
Requires-Dist: pypac
Requires-Dist: pyOpenSSL
Requires-Dist: google-api-core
Requires-Dist: importlib_resources
Requires-Dist: packageurl-python
Requires-Dist: pathspec
Requires-Dist: jsonschema
Requires-Dist: crc
Requires-Dist: protoc-gen-openapiv2
Requires-Dist: cyclonedx-python-lib[validation]
Provides-Extra: fast-winnowing
Requires-Dist: scanoss_winnowing>=0.5.0; extra == "fast-winnowing"
Dynamic: license-file
